Qdislib/__init__.py
Qdislib/api/__init__.py
Qdislib/api/api.py
Qdislib/core/__init__.py
Qdislib/core/cutting_algorithms/__init__.py
Qdislib/core/cutting_algorithms/gate_cutting.py
Qdislib/core/cutting_algorithms/wire_cutting.py
Qdislib/core/find_cut/__init__.py
Qdislib/core/find_cut/find_cut.py
Qdislib/core/graph_algorithms/__init__.py
Qdislib/core/graph_algorithms/random_graph_generator.py
Qdislib/core/qubit_mapping/__init__.py
Qdislib/core/qubit_mapping/qubit_mapping.py
Qdislib/utils/__init__.py
Qdislib/utils/circuit.py
Qdislib/utils/exceptions.py
Qdislib/utils/graph_qibo.py
Qdislib/utils/graph_qiskit.py
qdislib-1.0.0.dist-info/licenses/LICENSE
qdislib-1.0.0.dist-info/licenses/NOTICE
qdislib-1.0.0.dist-info/METADATA
qdislib-1.0.0.dist-info/WHEEL
qdislib-1.0.0.dist-info/top_level.txt
qdislib-1.0.0.dist-info/RECORD
