Metadata-Version: 2.4
Name: Qdislib
Version: 1.0.0
Summary: The quantum distributed computing library on top of PyCOMPSs
Author-email: "Workflows and Distributed Computing Group (WDC) - Barcelona Supercomputing Center (BSC)" <support-compss@bsc.es>
Maintainer-email: "Workflows and Distributed Computing Group (WDC) - Barcelona Supercomputing Center (BSC)" <support-compss@bsc.es>
License-Expression: Apache-2.0
Project-URL: Homepage, https://Qdislib.bsc.es
Project-URL: Documentation, https://Qdislib.readthedocs.io
Keywords: Quantum,distributed computing,PyCOMPSs,COMPSs,Qdislib
Classifier: Development Status :: 3 - Alpha
Classifier: Operating System :: Unix
Classifier: Operating System :: POSIX :: Linux
Classifier: Operating System :: MacOS
Classifier: Programming Language :: Python :: 3
Classifier: Programming Language :: Python :: 3.10
Classifier: Programming Language :: Python :: 3.11
Classifier: Programming Language :: Python :: 3.12
Classifier: Programming Language :: Python :: 3.13
Classifier: Programming Language :: Python :: 3 :: Only
Classifier: Intended Audience :: Science/Research
Classifier: Intended Audience :: Developers
Classifier: Intended Audience :: Information Technology
Classifier: Topic :: System :: Distributed Computing
Classifier: Topic :: Software Development :: Libraries
Classifier: Topic :: Software Development :: Libraries :: Python Modules
Requires-Python: >=3.10
License-File: LICENSE
License-File: NOTICE
Requires-Dist: rustworkx>=0.15.0
Requires-Dist: numpy<3,>=1.17
Requires-Dist: scipy>=1.5
Requires-Dist: sympy>=1.3
Requires-Dist: dill>=0.3
Requires-Dist: python-dateutil>=2.8.0
Requires-Dist: stevedore>=3.0.0
Requires-Dist: typing
Requires-Dist: typing-extensions
Requires-Dist: symengine<0.14,>=0.11
Requires-Dist: igraph>=0.11.8
Requires-Dist: qiskit>=1.1.0
Requires-Dist: qiskit-addon-cutting>=0.10.0
Requires-Dist: qiskit_aer>=0.15.1
Requires-Dist: qibo>=0.1.12
Requires-Dist: networkx>=3.1
Requires-Dist: matplotlib>=3.4.3
Requires-Dist: pymetis>=2023.1
Requires-Dist: scikit-learn
Provides-Extra: ci
Requires-Dist: pycodestyle; extra == "ci"
Requires-Dist: pydocstyle; extra == "ci"
Requires-Dist: black; extra == "ci"
Requires-Dist: flake8; extra == "ci"
Requires-Dist: bandit; extra == "ci"
Requires-Dist: pylint; extra == "ci"
Requires-Dist: prospector; extra == "ci"
Requires-Dist: pytest; extra == "ci"
Requires-Dist: pytest-cov[all]; extra == "ci"
Requires-Dist: nbsphinx; extra == "ci"
Requires-Dist: nbsphinx-link; extra == "ci"
Requires-Dist: sphinx-material; extra == "ci"
Requires-Dist: sphinx-mdinclude; extra == "ci"
Provides-Extra: notebooks
Requires-Dist: jupyter; extra == "notebooks"
Provides-Extra: qchip
Requires-Dist: qiboconnection>=0.12.0; extra == "qchip"
Provides-Extra: pycompss
Requires-Dist: pycompss; extra == "pycompss"
Requires-Dist: qiboconnection>=0.12.0; extra == "pycompss"
Dynamic: license-file
